Metadata-Version: 2.1
Name: dash-cookies
Version: 0.0.3
Summary: Project Description
Author: s_matsumoto <s_matsumoto@thinkup-sol.co.jp>
License: MIT
Classifier: Framework :: Dash
License-File: LICENSE
